LICENSE
MANIFEST.in
README.md
requirements.txt
setup.py
aiofilesearch.egg-info/PKG-INFO
aiofilesearch.egg-info/SOURCES.txt
aiofilesearch.egg-info/dependency_links.txt
aiofilesearch.egg-info/entry_points.txt
aiofilesearch.egg-info/requires.txt
aiofilesearch.egg-info/top_level.txt
aiofilesearch.egg-info/zip-safe
tmpo/__init__.py
tmpo/front/dist/front.7091cd83.css
tmpo/front/dist/front.7091cd83.js
tmpo/front/dist/front.7091cd83.map
tmpo/front/dist/index.html
tmpo/fsearch/__init__.py
tmpo/fsearch/main.py